flake8_vedro_mocks/__init__.py
flake8_vedro_mocks/config.py
flake8_vedro_mocks/plugins.py
flake8_vedro_mocks/abstract_checkers/__init__.py
flake8_vedro_mocks/abstract_checkers/scenario_helper.py
flake8_vedro_mocks/abstract_checkers/step_checker.py
flake8_vedro_mocks/errors/__init__.py
flake8_vedro_mocks/errors/errors.py
flake8_vedro_mocks/helpers/__init__.py
flake8_vedro_mocks/helpers/context_manager_with_position.py
flake8_vedro_mocks/helpers/get_nodes_from_functions.py
flake8_vedro_mocks/helpers/mock_assertions.py
flake8_vedro_mocks/helpers/self_attribute_assertions.py
flake8_vedro_mocks/types/__init__.py
flake8_vedro_mocks/types/types.py
flake8_vedro_mocks/visitors/__init__.py
flake8_vedro_mocks/visitors/_visitor_with_filename.py
flake8_vedro_mocks/visitors/scenario_visitor.py
flake8_vedro_mocks/visitors/steps_checkers/__init__.py
flake8_vedro_mocks/visitors/steps_checkers/mock_assert_checker.py
flake8_vedro_mocks-1.0.0.dist-info/LICENSE
flake8_vedro_mocks-1.0.0.dist-info/METADATA
flake8_vedro_mocks-1.0.0.dist-info/WHEEL
flake8_vedro_mocks-1.0.0.dist-info/entry_points.txt
flake8_vedro_mocks-1.0.0.dist-info/top_level.txt
flake8_vedro_mocks-1.0.0.dist-info/RECORD
