Metadata-Version: 2.1
Name: flake8-vedro-mocks
Version: 1.0.0
Summary: flake8 based linter for vedro framework and mocks
Home-page: https://github.com/FiruzShoev/flake8-vedro-mocks
Author: Firuz Shoev
Author-email: firuzshoevpy@gmail.com
License: Apache-2.0
Classifier: License :: OSI Approved :: Apache Software License
Classifier: Programming Language :: Python :: 3.10
Classifier: Programming Language :: Python :: 3.11
Requires-Python: >=3.10
License-File: LICENSE
Requires-Dist: flake8<7.0,>=6.0
Requires-Dist: flake8-plugin-utils<2.0,>=1.3.2
